<?xml version="1.0" encoding="iso-8859-1"?>

<!-- Parcel manifest for Pim Schema -->
<!-- $Revision$ -->
<!-- $Date$ -->
<!-- Copyright (c) 2003 Open Source Applications Foundation -->
<!-- License: http://osafoundation.org/Chandler_0.1_license_terms.htm -->

<Parcel itemName="PimSchema"
        xmlns="//Schema/Core"
        xmlns:pim="//Parcels/OSAF/PimSchema">

  <displayName>Pim Schema</displayName>
  <description>Pim schema for the 0.3 release</description>
  <version>0.3</version>
  <author>Open Source Applications Foundation</author>

<!-- Information Item -->
  <Attribute itemName="projects">
    <displayName>projects</displayName>
    <description>What project does this item belong to?</description>
    <cardinality>list</cardinality>
    <type itemref="pim:Project"/>
    <inverseAttribute itemref="pim:projectItems"/>
  </Attribute>

  <Attribute itemName="folders">
    <displayName>folders</displayName>
    <description>What folders is this item filed in?</description>
    <cardinality>list</cardinality>
    <type itemref="pim:Folder"/>
    <inverseAttribute itemref="pim:folderItems"/>
  </Attribute>
  
  <Attribute itemName="name">
    <displayName>name</displayName>
    <description>names of objects</description>
    <cardinality>single</cardinality>
    <type itemref="String"/>
  </Attribute>

  <Kind itemName="InformationItem">
    <displayName>Information Item</displayName>
    <examples>an Calendar Event -- 'Lunch with Tug'</examples>
    <examples>a Contact -- 'Terry Smith'</examples>
    <examples>a Task -- 'mail 1040 to IRS'</examples>
    <examples>a Sailing Ship -- 'The Beagle'</examples>
    <description>
      Items can appear in Views.
      Queries return collections of Items.
      Users can add attributes to Items.
      Everything is a type of Item.
    </description>
    <issues>@@@ -- add a categories attribute, to keep track of what 'virtual folders' the item appears in</issues>
    <superKinds itemref="Item"/>
    <attributes itemref="pim:projects"/>
    <attributes itemref="pim:folders"/>
  </Kind>


<!-- Project -->
  <Attribute itemName="parentProject">
    <displayName>parent project</displayName>
    <description>projects can be organized into hierarchies</description>
    <cardinality>single</cardinality>
    <type itemref="pim:Project"/>
    <inverseAttribute itemref="pim:subProjects"/>
  </Attribute>

  <Attribute itemName="subProjects">
    <displayName>sub projects</displayName>
    <description>projects can be organized into hierarchies</description>
    <cardinality>list</cardinality>
    <type itemref="pim:Project"/>
    <inverseAttribute itemref="pim:parentProject"/>
  </Attribute>

  <Attribute itemName="projectItems">
    <displayName>project items</displayName>
    <description>items can be organized into projects</description>
    <cardinality>list</cardinality>
    <type itemref="pim:InformationItem"/>
    <inverseAttribute itemref="pim:projects"/>
  </Attribute>

  <Kind itemName="Project">
    <displayName>Project</displayName>
    <superKinds itemref="Item"/>
    <attributes itemref="pim:name"/>
    <attributes itemref="description"/>
    <attributes itemref="pim:parentProject"/>
    <attributes itemref="pim:subProjects"/>
    <attributes itemref="pim:projectItems"/>
  </Kind>

<!-- Folder -->
  <Attribute itemName="folderItems">
    <displayName>folder items</displayName>
    <description>What's in the folder?</description>
    <cardinality>list</cardinality>
    <type itemref="Item"/>
  </Attribute>

  <Attribute itemName="folderType">
    <displayName>type</displayName>
    <description>What types of items should the folder be expected to hold?</description>
    <cardinality>list</cardinality>
    <type itemref="Taxon"/>
  </Attribute>

  <Kind itemName="Folder">
    <displayName>Folder</displayName>
    <examples>Inbox</examples>
    <examples>Sent</examples>
    <examples>Spam</examples>
    <examples>Work address list</examples>
    <examples>Drafts</examples>
    <examples>Recipes</examples>
    <examples>E-mail folders</examples>
    <examples>agent change log</examples>
    <examples>agent registry</examples>
    <examples>address book</examples>
    <examples>change log</examples>
    <description>
      A Folder represents a folder of e-mail messages (a mailbox) or a folder of any other type of Item.
    </description>
    <superKinds itemref="Item"/>
    <attributes itemref="pim:name"/>
    <attributes itemref="description"/>
    <attributes itemref="pim:folderItems"/>
    <attributes itemref="pim:folderType"/>
  </Kind>

</Parcel>
     