<?xml version="1.0" encoding="iso-8859-1"?>

<!-- $Revision$ -->
<!-- $Date$ -->
<!-- Copyright (c) 2003 Open Source Applications Foundation -->
<!-- License: http://osafoundation.org/Chandler_0.1_license_terms.htm -->

<core:Parcel describes="//parcels/OSAF/views/zaobao"
             itemName="zaobao"
             xmlns:core="//Schema/Core"
             xmlns="//parcels/OSAF/framework/blocks"
             xmlns:doc="//parcels/OSAF/views/zaobao"
             xmlns:events="//parcels/OSAF/framework/blocks/Events"
             xmlns:zb="//parcels/OSAF/examples/zaobao">

  <core:version>0.3</core:version>

  <!-- RSS Channels -->
  <zb:RSSChannel itemName="osaf">
    <zb:url>http://www.osafoundation.org/rss/2.0/</zb:url>
  </zb:RSSChannel>
  <zb:RSSChannel itemName="ted">
    <zb:url>http://www.sauria.com/blog?flav=rss</zb:url>
  </zb:RSSChannel>

  <!-- Queries -->
  <Query itemName="myQuery">
    <queryEnum>listOfItems</queryEnum>
    <data>//parcels/OSAF/views/zaobao/osaf.items</data>
  </Query>

  <!-- Styles -->
  <CharacterStyle itemName="HeaderCharacterStyle">
    <fontFamily>DefaultUIFont</fontFamily>
    <fontSize>12.0</fontSize>
    <fontStyle>bold</fontStyle>
    <fontName></fontName>
  </CharacterStyle>  

  <!-- Events -->

  <!-- Menus -->

  <!-- Menu Items -->


  <!-- The main ZaoBao view -->

  <Tree itemName="ZaoBaoTree">
    <elementDelegate>OSAF.examples.zaobao.blocks.ZaoBaoTreeDelegate</elementDelegate>
    <rootPath itemref="zb:RSSChannel"/>
    <hideRoot>True</hideRoot>
    <noLines>True</noLines>
    <useButtons>True</useButtons>

    <columnHeadings>Subject</columnHeadings>
    <columnWidths>300</columnWidths>
    <columnHeadings>Date</columnHeadings>
    <columnWidths>150</columnWidths>

    <size>600,200</size>
    <minimumSize>400,100</minimumSize>
    <border>0.0, 0.0, 0.0, 0.0</border>
    <alignmentEnum>grow</alignmentEnum>
    <stretchFactor>1.0</stretchFactor>
  </Tree>

  <zb:ZaoBaoItemDetail itemName="ItemDetail">
    <open>True</open>
    <size>100,50</size>
    <minimumSize>100,50</minimumSize>
    <border>0.0, 0.0, 0.0, 0.0</border>
    <alignmentEnum>grow</alignmentEnum>
    <stretchFactor>1.0</stretchFactor>
  </zb:ZaoBaoItemDetail>

  <EditText itemName="NewChannel">
    <open>True</open>
    <size>100,20</size>
    <minimumSize>100,20</minimumSize>
    <border>3.0, 3.0, 3.0, 3.0</border>
    <alignmentEnum>grow</alignmentEnum>
    <stretchFactor>0.0</stretchFactor>
    <textAlignmentEnum>Left</textAlignmentEnum>
    <lineStyleEnum>SingleLine</lineStyleEnum>
    <textStyleEnum>PlainText</textStyleEnum>
    <readOnly>False</readOnly>
    <characterStyle itemref="doc:HeaderCharacterStyle"/>
  </EditText>

  <BoxContainer itemName="ItemViewBox">
    <open>True</open>
    <size>200,100</size>
    <minimumSize>200,100</minimumSize>
    <border>2.0, 2.0, 2.0, 2.0</border>
    <alignmentEnum>grow</alignmentEnum>
    <stretchFactor>1.0</stretchFactor>
    <orientationEnum>Vertical</orientationEnum>

    <childrenBlocks itemref="doc:ItemDetail"/>
    <childrenBlocks itemref="doc:NewChannel"/>

  </BoxContainer>

  <SplitWindow itemName="ZaoBaoView">
    <orientationEnum>Horizontal</orientationEnum>
    <splitPercentage>0.5</splitPercentage>
    
    <eventBoundary>True</eventBoundary>
    <open>True</open>
    <size>900,580</size>
    <minimumSize>900,580</minimumSize>
    <border>2.0, 2.0, 2.0, 2.0</border>
    <alignmentEnum>grow</alignmentEnum>
    <stretchFactor>1.0</stretchFactor>

    <childrenBlocks itemref="doc:ZaoBaoTree"/>
    <childrenBlocks itemref="doc:ItemViewBox"/>
  </SplitWindow>








  <!-- Example single channel view -->

  <Tree itemName="ChannelList">
    <elementDelegate>OSAF.examples.zaobao.blocks.ZaoBaoListDelegate</elementDelegate>
    <rootPath itemref="doc:osaf"/>
    <hideRoot>True</hideRoot>
    <noLines>True</noLines>
    <useButtons>True</useButtons>

    <columnHeadings>Subject</columnHeadings>
    <columnWidths>300</columnWidths>
    <columnHeadings>Date</columnHeadings>
    <columnWidths>150</columnWidths>

    <size>600,200</size>
    <minimumSize>400,100</minimumSize>
    <border>0.0, 0.0, 0.0, 0.0</border>
    <alignmentEnum>grow</alignmentEnum>
    <stretchFactor>1.0</stretchFactor>
  </Tree>

  <zb:ZaoBaoItemDetail itemName="ChannelItemDetail">
    <open>True</open>
    <size>100,50</size>
    <minimumSize>100,50</minimumSize>
    <border>0.0, 0.0, 0.0, 0.0</border>
    <alignmentEnum>grow</alignmentEnum>
    <stretchFactor>1.0</stretchFactor>
  </zb:ZaoBaoItemDetail>


  <SplitWindow itemName="ZaoBaoChannelView">
    <orientationEnum>Horizontal</orientationEnum>
    <splitPercentage>0.5</splitPercentage>
    
    <eventBoundary>True</eventBoundary>
    <open>True</open>
    <size>900,580</size>
    <minimumSize>900,580</minimumSize>
    <border>2.0, 2.0, 2.0, 2.0</border>
    <alignmentEnum>grow</alignmentEnum>
    <stretchFactor>1.0</stretchFactor>

    <childrenBlocks itemref="doc:ChannelList"/>
    <childrenBlocks itemref="doc:ChannelItemDetail"/>
  </SplitWindow>
  
</core:Parcel>
